divisibility_checker.sv
module divisibility_checker (
  input clk
);
  
  // State Machine params
  parameter S_COMP = 0; // Comparing the divisor and divident
  parameter S_SUB = 1; // Subtracting whatever from whatever else
  parameter S_END = 2; // The final verdict

  reg [1:0] state = 0;


  parameter NUMBER_LENGTH = 9;

  // Divisor and divident are representen in reverse (so MSB is actually LSB).
  reg [NUMBER_LENGTH-1:0] divisor = 9'd14;
  reg [NUMBER_LENGTH-1:0] divident = 9'd503;
  
  reg [10:0] index = 0; // This will eventually be chunk index

  reg comp_bit_divident;
  reg comp_bit_divisor;
  reg [1:0] comp_result;

  reg sub_res = 0;
  reg borrow = 0;
  reg sub_a = 0;
  reg sub_b = 0;

  reg [31:0] shifted = 0;
  always @ (posedge clk) begin
    case (state)
      S_COMP: begin
        comp_bit_divident = divident[NUMBER_LENGTH-index-1]; // This will eventually be a memory fetch
        comp_bit_divisor = divisor[NUMBER_LENGTH-index-1-shifted]; // This will eventually be a memory fetch
        comp_result = {comp_bit_divisor == comp_bit_divident, comp_bit_divident > comp_bit_divisor};
        case (comp_result)
          2'b00: begin
            // divisor is larger than divident
            // if it's shifted, shift it back once and subtract
            // else, go to end condition
            if (shifted) begin
              shifted <= shifted - 1;
              $display("Switching to SUB mode");
              state = S_SUB;
              index = 0;
            end else begin
              $display("Switching to END mode");
              state = S_END;
              index = 0;
            end
          end
          2'b10: begin
            // divisor and divident are equal up to that bit
            index = index + 1;
          end
          default: begin 
            // divident is still larger than divisor.
            // if the first bits are different, shift again
            // else, go to sub
            if (index) begin
              $display("Switching to SUB mode");
              state = S_SUB;
            end else begin
              shifted = shifted + 1;
            end
            index = 0;
          end
        endcase

      end
      S_SUB: begin
        sub_a = divident[index];
        if (index >= shifted) begin
          sub_b = divisor[index-shifted];
        end else begin
          sub_b = 0;
        end
        sub_res = (sub_a^sub_b)^borrow;
        borrow = (~sub_a)&sub_b | borrow&(~(sub_a^sub_b));
        divident[index] = sub_res;
        if (index == NUMBER_LENGTH-1) begin
          state = S_COMP;
          $display("Switching to COMP mode");
          index = 0;
          shifted = 0;
        end else begin
          index = index + 1;
        end
      end
      default : begin
        $display("Total mod: %d", divident);
      end

    endcase
  end
  
endmodule

testbench.sv
module testbench (
  
);
  
  reg clk = 0;

  divisibility_checker uut (
    .clk (clk)
    );

  initial begin
    $dumpfile("dump.vcd");
    $dumpvars(0, testbench);
    #10000 $finish;
  end

  always #5 clk <= ~clk;
endmodule

dump.vcd
$date
	Wed Mar 27 16:09:38 2024
$end
$version
	Icarus Verilog
$end
$timescale
	1s
$end
$scope module testbench $end
$var reg 1 ! clk $end
$scope module uut $end
$var wire 1 ! clk $end
$var parameter 32 " NUMBER_LENGTH $end
$var parameter 32 # S_COMP $end
$var parameter 32 $ S_END $end
$var parameter 32 % S_SUB $end
$var reg 1 & borrow $end
$var reg 1 ' comp_bit_divident $end
$var reg 1 ( comp_bit_divisor $end
$var reg 2 ) comp_result [1:0] $end
$var reg 9 * divident [8:0] $end
$var reg 9 + divisor [8:0] $end
$var reg 11 , index [10:0] $end
$var reg 32 - shifted [31:0] $end
$var reg 2 . state [1:0] $end
$var reg 1 / sub_a $end
$var reg 1 0 sub_b $end
$var reg 1 1 sub_res $end
$upscope $end
$upscope $end
$enddefinitions $end
$comment Show the parameter values. $end
$dumpall
b1 %
b10 $
b0 #
b1001 "
$end
#0
$dumpvars
01
00
0/
b0 .
b0 -
b0 ,
b1110 +
b111110111 *
bx )
x(
x'
0&
0!
$end
#5
b1 -
b1 )
0(
1'
1!
#10
0!
#15
b10 -
1!
#20
0!
#25
b11 -
1!
#30
0!
#35
b100 -
1!
#40
0!
#45
b101 -
1!
#50
0!
#55
b1 ,
b10 )
1(
1!
#60
0!
#65
b10 ,
1!
#70
0!
#75
b11 ,
1!
#80
0!
#85
b0 ,
b1 .
b1 )
0(
1!
#90
0!
#95
b1 ,
11
1/
1!
#100
0!
#105
b10 ,
1!
#110
0!
#115
b11 ,
1!
#120
0!
#125
b100 ,
01
0/
1!
#130
0!
#135
b101 ,
11
1/
1!
#140
0!
#145
b110 ,
1!
#150
0!
#155
b111 ,
b110110111 *
01
10
1!
#160
0!
#165
b1000 ,
b100110111 *
1!
#170
0!
#175
b0 -
b0 ,
b0 .
b110111 *
1!
#180
0!
#185
b1 ,
b10 )
0'
1!
#190
0!
#195
b10 ,
1!
#200
0!
#205
b11 ,
1!
#210
0!
#215
b0 ,
b1 .
b1 )
1'
1!
#220
0!
#225
b1 ,
11
00
1!
#230
0!
#235
b10 ,
b110101 *
01
10
1!
#240
0!
#245
b11 ,
b110001 *
1!
#250
0!
#255
b100 ,
b111001 *
1&
11
0/
1!
#260
0!
#265
b101 ,
b101001 *
0&
01
00
1/
1!
#270
0!
#275
b110 ,
11
1!
#280
0!
#285
b111 ,
01
0/
1!
#290
0!
#295
b1000 ,
1!
#300
0!
#305
b0 ,
b0 .
1!
#310
0!
#315
b1 ,
b10 )
0'
1!
#320
0!
#325
b10 ,
1!
#330
0!
#335
b11 ,
1!
#340
0!
#345
b0 ,
b1 .
b1 )
1'
1!
#350
0!
#355
b1 ,
11
1/
1!
#360
0!
#365
b10 ,
b101011 *
1&
10
0/
1!
#370
0!
#375
b11 ,
01
1!
#380
0!
#385
b100 ,
11
1/
1!
#390
0!
#395
b101 ,
b111011 *
00
0/
1!
#400
0!
#405
b110 ,
b11011 *
0&
01
1/
1!
#410
0!
#415
b111 ,
0/
1!
#420
0!
#425
b1000 ,
1!
#430
0!
#435
b0 ,
b0 .
1!
#440
0!
#445
b1 ,
b10 )
0'
1!
#450
0!
#455
b10 ,
1!
#460
0!
#465
b11 ,
1!
#470
0!
#475
b100 ,
1!
#480
0!
#485
b0 ,
b1 .
b1 )
1'
1!
#490
0!
#495
b1 ,
11
1/
1!
#500
0!
#505
b10 ,
b11001 *
01
10
1!
#510
0!
#515
b11 ,
b11101 *
1&
11
0/
1!
#520
0!
#525
b100 ,
1/
1!
#530
0!
#535
b101 ,
b1101 *
0&
01
00
1!
#540
0!
#545
b110 ,
0/
1!
#550
0!
#555
b111 ,
1!
#560
0!
#565
b1000 ,
1!
#570
0!
#575
b0 ,
b0 .
1!
#580
0!
#585
b1 ,
b10 )
0'
1!
#590
0!
#595
b10 ,
1!
#600
0!
#605
b11 ,
1!
#610
0!
#615
b100 ,
1!
#620
0!
#625
b101 ,
1!
#630
0!
#635
b110 ,
1(
1'
1!
#640
0!
#645
b111 ,
1!
#650
0!
#655
b0 ,
b10 .
b0 )
0'
1!
