divisibility_checker.sv
module divisibility_checker (
  input clk
);
  
  // State Machine params
  parameter S_COMP = 0; // Comparing the divisor and divident
  parameter S_SUB = 1; // Subtracting whatever from whatever else
  parameter S_END = 2; // The final verdict

  reg [1:0] state = 0;


  parameter NUMBER_LENGTH = 9;

  // Divisor and divident are representen in reverse (so MSB is actually LSB).
  reg [NUMBER_LENGTH-1:0] divisor = 9'd14;
  reg [NUMBER_LENGTH-1:0] divident = 9'd503;
  
  reg [10:0] index = 0; // This will eventually be chunk index

  reg comp_bit_divident;
  reg comp_bit_divisor;
  reg [1:0] comp_result;

  reg sub_res = 0;
  reg borrow = 0;
  reg sub_a = 0;
  reg sub_b = 0;

  always @ (posedge clk) begin
    case (state)
      S_COMP: begin
        comp_bit_divident = divident[NUMBER_LENGTH-index-1]; // This will eventually be a memory fetch
        comp_bit_divisor = divisor[NUMBER_LENGTH-index-1]; // This will eventually be a memory fetch
        comp_result = {comp_bit_divisor == comp_bit_divident, comp_bit_divident > comp_bit_divisor};
        case (comp_result)
          2'b01: begin 
            $display("Switching to SUB mode");
            index = 0;
            state = S_SUB;
          end
          2'b00: begin 
            $display("Switching to END mode");
            state = S_END;
            index <= 0;
          end
          default : begin
            index <= index + 1;
          end
        endcase

      end
      S_SUB: begin
        sub_a = divident[index];
        sub_b = divisor[index];

        sub_res = (sub_a^sub_b)^borrow;
        borrow = (~sub_a)&sub_b | borrow&(~(sub_a^sub_b));
        divident[index] = sub_res;
        if (index == NUMBER_LENGTH-1) begin
          state = S_COMP;
          $display("Switching to COMP mode");
          index = 0;
        end else begin
          index = index + 1;
        end
      end
      default : begin
        $display("Total mod: %d", divident);
      end

    endcase
  end
  
endmodule

testbench.sv
module testbench (
  
);
  
  reg clk = 0;

  divisibility_checker uut (
    .clk (clk)
    );

  initial begin
    $dumpfile("dump.vcd");
    $dumpvars(0, testbench);
    #10000 $finish;
  end

  always #5 clk <= ~clk;
endmodule

dump.vcd
$date
	Wed Mar 27 15:33:42 2024
$end
$version
	Icarus Verilog
$end
$timescale
	1s
$end
$scope module testbench $end
$var reg 1 ! clk $end
$scope module uut $end
$var wire 1 ! clk $end
$var parameter 32 " NUMBER_LENGTH $end
$var parameter 32 # S_COMP $end
$var parameter 32 $ S_END $end
$var parameter 32 % S_SUB $end
$var reg 1 & borrow $end
$var reg 1 ' comp_bit_divident $end
$var reg 1 ( comp_bit_divisor $end
$var reg 2 ) comp_result [1:0] $end
$var reg 9 * divident [8:0] $end
$var reg 9 + divisor [8:0] $end
$var reg 11 , index [10:0] $end
$var reg 2 - state [1:0] $end
$var reg 1 . sub_a $end
$var reg 1 / sub_b $end
$var reg 1 0 sub_res $end
$upscope $end
$upscope $end
$enddefinitions $end
$comment Show the parameter values. $end
$dumpall
b1 %
b10 $
b0 #
b1001 "
$end
#0
$dumpvars
00
0/
0.
b0 -
b0 ,
b1110 +
b111110111 *
bx )
x(
x'
0&
0!
$end
#5
b1 -
b1 )
0(
1'
1!
#10
0!
#15
b1 ,
10
1.
1!
#20
0!
#25
b10 ,
b111110101 *
00
1/
1!
#30
0!
#35
b11 ,
b111110001 *
1!
#40
0!
#45
b100 ,
b111111001 *
1&
10
0.
1!
#50
0!
#55
b101 ,
b111101001 *
0&
00
0/
1.
1!
#60
0!
#65
b110 ,
10
1!
#70
0!
#75
b111 ,
1!
#80
0!
#85
b1000 ,
1!
#90
0!
#95
b0 ,
b0 -
1!
#100
0!
#105
b1 -
1!
#110
0!
#115
b1 ,
1!
#120
0!
#125
b10 ,
b111101011 *
1&
1/
0.
1!
#130
0!
#135
b11 ,
00
1!
#140
0!
#145
b100 ,
10
1.
1!
#150
0!
#155
b101 ,
b111111011 *
0/
0.
1!
#160
0!
#165
b110 ,
b111011011 *
0&
00
1.
1!
#170
0!
#175
b111 ,
10
1!
#180
0!
#185
b1000 ,
1!
#190
0!
#195
b0 ,
b0 -
1!
#200
0!
#205
b1 -
1!
#210
0!
#215
b1 ,
1!
#220
0!
#225
b10 ,
b111011001 *
00
1/
1!
#230
0!
#235
b11 ,
b111011101 *
1&
10
0.
1!
#240
0!
#245
b100 ,
1.
1!
#250
0!
#255
b101 ,
b111001101 *
0&
00
0/
1!
#260
0!
#265
b110 ,
0.
1!
#270
0!
#275
b111 ,
10
1.
1!
#280
0!
#285
b1000 ,
1!
#290
0!
#295
b0 ,
b0 -
1!
#300
0!
#305
b1 -
1!
#310
0!
#315
b1 ,
1!
#320
0!
#325
b10 ,
b111001111 *
1&
1/
0.
1!
#330
0!
#335
b11 ,
1.
1!
#340
0!
#345
b100 ,
1!
#350
0!
#355
b101 ,
b111011111 *
0/
0.
1!
#360
0!
#365
b110 ,
b111111111 *
1!
#370
0!
#375
b111 ,
b110111111 *
0&
00
1.
1!
#380
0!
#385
b1000 ,
10
1!
#390
0!
#395
b0 ,
b0 -
1!
#400
0!
#405
b1 -
1!
#410
0!
#415
b1 ,
1!
#420
0!
#425
b10 ,
b110111101 *
00
1/
1!
#430
0!
#435
b11 ,
b110111001 *
1!
#440
0!
#445
b100 ,
b110110001 *
1!
#450
0!
#455
b101 ,
10
0/
1!
#460
0!
#465
b110 ,
1!
#470
0!
#475
b111 ,
00
0.
1!
#480
0!
#485
b1000 ,
10
1.
1!
#490
0!
#495
b0 ,
b0 -
1!
#500
0!
#505
b1 -
1!
#510
0!
#515
b1 ,
1!
#520
0!
#525
b10 ,
b110110011 *
1&
1/
0.
1!
#530
0!
#535
b11 ,
00
1!
#540
0!
#545
b100 ,
1!
#550
0!
#555
b101 ,
b110100011 *
0&
0/
1.
1!
#560
0!
#565
b110 ,
10
1!
#570
0!
#575
b111 ,
00
0.
1!
#580
0!
#585
b1000 ,
10
1.
1!
#590
0!
#595
b0 ,
b0 -
1!
#600
0!
#605
b1 -
1!
#610
0!
#615
b1 ,
1!
#620
0!
#625
b10 ,
b110100001 *
00
1/
1!
#630
0!
#635
b11 ,
b110100101 *
1&
10
0.
1!
#640
0!
#645
b100 ,
00
1!
#650
0!
#655
b101 ,
b110110101 *
10
0/
1!
#660
0!
#665
b110 ,
b110010101 *
0&
00
1.
1!
#670
0!
#675
b111 ,
0.
1!
#680
0!
#685
b1000 ,
10
1.
1!
#690
0!
#695
b0 ,
b0 -
1!
#700
0!
#705
b1 -
1!
#710
0!
#715
b1 ,
1!
#720
0!
#725
b10 ,
b110010111 *
1&
1/
0.
1!
#730
0!
#735
b11 ,
1.
1!
#740
0!
#745
b100 ,
00
0.
1!
#750
0!
#755
b101 ,
b110000111 *
0&
0/
1.
1!
#760
0!
#765
b110 ,
0.
1!
#770
0!
#775
b111 ,
1!
#780
0!
#785
b1000 ,
10
1.
1!
#790
0!
#795
b0 ,
b0 -
1!
#800
0!
#805
b1 -
1!
#810
0!
#815
b1 ,
1!
#820
0!
#825
b10 ,
b110000101 *
00
1/
1!
#830
0!
#835
b11 ,
b110000001 *
1!
#840
0!
#845
b100 ,
b110001001 *
1&
10
0.
1!
#850
0!
#855
b101 ,
b110011001 *
0/
1!
#860
0!
#865
b110 ,
b110111001 *
1!
#870
0!
#875
b111 ,
b111111001 *
1!
#880
0!
#885
b1000 ,
b101111001 *
0&
00
1.
1!
#890
0!
#895
b0 ,
b0 -
10
1!
#900
0!
#905
b1 -
1!
#910
0!
#915
b1 ,
1!
#920
0!
#925
b10 ,
b101111011 *
1&
1/
0.
1!
#930
0!
#935
b11 ,
00
1!
#940
0!
#945
b100 ,
10
1.
1!
#950
0!
#955
b101 ,
b101101011 *
0&
00
0/
1!
#960
0!
#965
b110 ,
10
1!
#970
0!
#975
b111 ,
1!
#980
0!
#985
b1000 ,
00
0.
1!
#990
0!
#995
b0 ,
b0 -
10
1.
1!
#1000
0!
#1005
b1 -
1!
#1010
0!
#1015
b1 ,
1!
#1020
0!
#1025
b10 ,
b101101001 *
00
1/
1!
#1030
0!
#1035
b11 ,
b101101101 *
1&
10
0.
1!
#1040
0!
#1045
b100 ,
1.
1!
#1050
0!
#1055
b101 ,
b101111101 *
0/
0.
1!
#1060
0!
#1065
b110 ,
b101011101 *
0&
00
1.
1!
#1070
0!
#1075
b111 ,
10
1!
#1080
0!
#1085
b1000 ,
00
0.
1!
#1090
0!
#1095
b0 ,
b0 -
10
1.
1!
#1100
0!
#1105
b1 -
1!
#1110
0!
#1115
b1 ,
1!
#1120
0!
#1125
b10 ,
b101011111 *
1&
1/
0.
1!
#1130
0!
#1135
b11 ,
1.
1!
#1140
0!
#1145
b100 ,
1!
#1150
0!
#1155
b101 ,
b101001111 *
0&
00
0/
1!
#1160
0!
#1165
b110 ,
0.
1!
#1170
0!
#1175
b111 ,
10
1.
1!
#1180
0!
#1185
b1000 ,
00
0.
1!
#1190
0!
#1195
b0 ,
b0 -
10
1.
1!
#1200
0!
#1205
b1 -
1!
#1210
0!
#1215
b1 ,
1!
#1220
0!
#1225
b10 ,
b101001101 *
00
1/
1!
#1230
0!
#1235
b11 ,
b101001001 *
1!
#1240
0!
#1245
b100 ,
b101000001 *
1!
#1250
0!
#1255
b101 ,
0/
0.
1!
#1260
0!
#1265
b110 ,
1!
#1270
0!
#1275
b111 ,
10
1.
1!
#1280
0!
#1285
b1000 ,
00
0.
1!
#1290
0!
#1295
b0 ,
b0 -
10
1.
1!
#1300
0!
#1305
b1 -
1!
#1310
0!
#1315
b1 ,
1!
#1320
0!
#1325
b10 ,
b101000011 *
1&
1/
0.
1!
#1330
0!
#1335
b11 ,
00
1!
#1340
0!
#1345
b100 ,
1!
#1350
0!
#1355
b101 ,
b101010011 *
10
0/
1!
#1360
0!
#1365
b110 ,
b101110011 *
1!
#1370
0!
#1375
b111 ,
b100110011 *
0&
00
1.
1!
#1380
0!
#1385
b1000 ,
0.
1!
#1390
0!
#1395
b0 ,
b0 -
10
1.
1!
#1400
0!
#1405
b1 -
1!
#1410
0!
#1415
b1 ,
1!
#1420
0!
#1425
b10 ,
b100110001 *
00
1/
1!
#1430
0!
#1435
b11 ,
b100110101 *
1&
10
0.
1!
#1440
0!
#1445
b100 ,
00
1!
#1450
0!
#1455
b101 ,
b100100101 *
0&
0/
1.
1!
#1460
0!
#1465
b110 ,
10
1!
#1470
0!
#1475
b111 ,
00
0.
1!
#1480
0!
#1485
b1000 ,
1!
#1490
0!
#1495
b0 ,
b0 -
10
1.
1!
#1500
0!
#1505
b1 -
1!
#1510
0!
#1515
b1 ,
1!
#1520
0!
#1525
b10 ,
b100100111 *
1&
1/
0.
1!
#1530
0!
#1535
b11 ,
1.
1!
#1540
0!
#1545
b100 ,
00
0.
1!
#1550
0!
#1555
b101 ,
b100110111 *
10
0/
1!
#1560
0!
#1565
b110 ,
b100010111 *
0&
00
1.
1!
#1570
0!
#1575
b111 ,
0.
1!
#1580
0!
#1585
b1000 ,
1!
#1590
0!
#1595
b0 ,
b0 -
10
1.
1!
#1600
0!
#1605
b1 -
1!
#1610
0!
#1615
b1 ,
1!
#1620
0!
#1625
b10 ,
b100010101 *
00
1/
1!
#1630
0!
#1635
b11 ,
b100010001 *
1!
#1640
0!
#1645
b100 ,
b100011001 *
1&
10
0.
1!
#1650
0!
#1655
b101 ,
b100001001 *
0&
00
0/
1.
1!
#1660
0!
#1665
b110 ,
0.
1!
#1670
0!
#1675
b111 ,
1!
#1680
0!
#1685
b1000 ,
1!
#1690
0!
#1695
b0 ,
b0 -
10
1.
1!
#1700
0!
#1705
b1 -
1!
#1710
0!
#1715
b1 ,
1!
#1720
0!
#1725
b10 ,
b100001011 *
1&
1/
0.
1!
#1730
0!
#1735
b11 ,
00
1!
#1740
0!
#1745
b100 ,
10
1.
1!
#1750
0!
#1755
b101 ,
b100011011 *
0/
0.
1!
#1760
0!
#1765
b110 ,
b100111011 *
1!
#1770
0!
#1775
b111 ,
b101111011 *
1!
#1780
0!
#1785
b1000 ,
b111111011 *
1!
#1790
0!
#1795
b0 ,
b0 -
b11111011 *
0&
00
1.
1!
#1800
0!
#1805
b1 ,
b10 )
0'
1!
#1810
0!
#1815
b1 -
b0 ,
b1 )
1'
1!
#1820
0!
#1825
b1 ,
10
1!
#1830
0!
#1835
b10 ,
b11111001 *
00
1/
1!
#1840
0!
#1845
b11 ,
b11111101 *
1&
10
0.
1!
#1850
0!
#1855
b100 ,
1.
1!
#1860
0!
#1865
b101 ,
b11101101 *
0&
00
0/
1!
#1870
0!
#1875
b110 ,
10
1!
#1880
0!
#1885
b111 ,
1!
#1890
0!
#1895
b1000 ,
1!
#1900
0!
#1905
b0 ,
b0 -
00
0.
1!
#1910
0!
#1915
b1 ,
b10 )
0'
1!
#1920
0!
#1925
b1 -
b0 ,
b1 )
1'
1!
#1930
0!
#1935
b1 ,
10
1.
1!
#1940
0!
#1945
b10 ,
b11101111 *
1&
1/
0.
1!
#1950
0!
#1955
b11 ,
1.
1!
#1960
0!
#1965
b100 ,
1!
#1970
0!
#1975
b101 ,
b11111111 *
0/
0.
1!
#1980
0!
#1985
b110 ,
b11011111 *
0&
00
1.
1!
#1990
0!
#1995
b111 ,
10
1!
#2000
0!
#2005
b1000 ,
1!
#2010
0!
#2015
b0 ,
b0 -
00
0.
1!
#2020
0!
#2025
b1 ,
b10 )
0'
1!
#2030
0!
#2035
b1 -
b0 ,
b1 )
1'
1!
#2040
0!
#2045
b1 ,
10
1.
1!
#2050
0!
#2055
b10 ,
b11011101 *
00
1/
1!
#2060
0!
#2065
b11 ,
b11011001 *
1!
#2070
0!
#2075
b100 ,
b11010001 *
1!
#2080
0!
#2085
b101 ,
10
0/
1!
#2090
0!
#2095
b110 ,
00
0.
1!
#2100
0!
#2105
b111 ,
10
1.
1!
#2110
0!
#2115
b1000 ,
1!
#2120
0!
#2125
b0 ,
b0 -
00
0.
1!
#2130
0!
#2135
b1 ,
b10 )
0'
1!
#2140
0!
#2145
b1 -
b0 ,
b1 )
1'
1!
#2150
0!
#2155
b1 ,
10
1.
1!
#2160
0!
#2165
b10 ,
b11010011 *
1&
1/
0.
1!
#2170
0!
#2175
b11 ,
00
1!
#2180
0!
#2185
b100 ,
1!
#2190
0!
#2195
b101 ,
b11000011 *
0&
0/
1.
1!
#2200
0!
#2205
b110 ,
0.
1!
#2210
0!
#2215
b111 ,
10
1.
1!
#2220
0!
#2225
b1000 ,
1!
#2230
0!
#2235
b0 ,
b0 -
00
0.
1!
#2240
0!
#2245
b1 ,
b10 )
0'
1!
#2250
0!
#2255
b1 -
b0 ,
b1 )
1'
1!
#2260
0!
#2265
b1 ,
10
1.
1!
#2270
0!
#2275
b10 ,
b11000001 *
00
1/
1!
#2280
0!
#2285
b11 ,
b11000101 *
1&
10
0.
1!
#2290
0!
#2295
b100 ,
00
1!
#2300
0!
#2305
b101 ,
b11010101 *
10
0/
1!
#2310
0!
#2315
b110 ,
b11110101 *
1!
#2320
0!
#2325
b111 ,
b10110101 *
0&
00
1.
1!
#2330
0!
#2335
b1000 ,
10
1!
#2340
0!
#2345
b0 ,
b0 -
00
0.
1!
#2350
0!
#2355
b1 ,
b10 )
0'
1!
#2360
0!
#2365
b1 -
b0 ,
b1 )
1'
1!
#2370
0!
#2375
b1 ,
10
1.
1!
#2380
0!
#2385
b10 ,
b10110111 *
1&
1/
0.
1!
#2390
0!
#2395
b11 ,
1.
1!
#2400
0!
#2405
b100 ,
00
0.
1!
#2410
0!
#2415
b101 ,
b10100111 *
0&
0/
1.
1!
#2420
0!
#2425
b110 ,
10
1!
#2430
0!
#2435
b111 ,
00
0.
1!
#2440
0!
#2445
b1000 ,
10
1.
1!
#2450
0!
#2455
b0 ,
b0 -
00
0.
1!
#2460
0!
#2465
b1 ,
b10 )
0'
1!
#2470
0!
#2475
b1 -
b0 ,
b1 )
1'
1!
#2480
0!
#2485
b1 ,
10
1.
1!
#2490
0!
#2495
b10 ,
b10100101 *
00
1/
1!
#2500
0!
#2505
b11 ,
b10100001 *
1!
#2510
0!
#2515
b100 ,
b10101001 *
1&
10
0.
1!
#2520
0!
#2525
b101 ,
b10111001 *
0/
1!
#2530
0!
#2535
b110 ,
b10011001 *
0&
00
1.
1!
#2540
0!
#2545
b111 ,
0.
1!
#2550
0!
#2555
b1000 ,
10
1.
1!
#2560
0!
#2565
b0 ,
b0 -
00
0.
1!
#2570
0!
#2575
b1 ,
b10 )
0'
1!
#2580
0!
#2585
b1 -
b0 ,
b1 )
1'
1!
#2590
0!
#2595
b1 ,
10
1.
1!
#2600
0!
#2605
b10 ,
b10011011 *
1&
1/
0.
1!
#2610
0!
#2615
b11 ,
00
1!
#2620
0!
#2625
b100 ,
10
1.
1!
#2630
0!
#2635
b101 ,
b10001011 *
0&
00
0/
1!
#2640
0!
#2645
b110 ,
0.
1!
#2650
0!
#2655
b111 ,
1!
#2660
0!
#2665
b1000 ,
10
1.
1!
#2670
0!
#2675
b0 ,
b0 -
00
0.
1!
#2680
0!
#2685
b1 ,
b10 )
0'
1!
#2690
0!
#2695
b1 -
b0 ,
b1 )
1'
1!
#2700
0!
#2705
b1 ,
10
1.
1!
#2710
0!
#2715
b10 ,
b10001001 *
00
1/
1!
#2720
0!
#2725
b11 ,
b10001101 *
1&
10
0.
1!
#2730
0!
#2735
b100 ,
1.
1!
#2740
0!
#2745
b101 ,
b10011101 *
0/
0.
1!
#2750
0!
#2755
b110 ,
b10111101 *
1!
#2760
0!
#2765
b111 ,
b11111101 *
1!
#2770
0!
#2775
b1000 ,
b1111101 *
0&
00
1.
1!
#2780
0!
#2785
b0 ,
b0 -
0.
1!
#2790
0!
#2795
b1 ,
b10 )
0'
1!
#2800
0!
#2805
b10 ,
1!
#2810
0!
#2815
b1 -
b0 ,
b1 )
1'
1!
#2820
0!
#2825
b1 ,
10
1.
1!
#2830
0!
#2835
b10 ,
b1111111 *
1&
1/
0.
1!
#2840
0!
#2845
b11 ,
1.
1!
#2850
0!
#2855
b100 ,
1!
#2860
0!
#2865
b101 ,
b1101111 *
0&
00
0/
1!
#2870
0!
#2875
b110 ,
10
1!
#2880
0!
#2885
b111 ,
1!
#2890
0!
#2895
b1000 ,
00
0.
1!
#2900
0!
#2905
b0 ,
b0 -
1!
#2910
0!
#2915
b1 ,
b10 )
0'
1!
#2920
0!
#2925
b10 ,
1!
#2930
0!
#2935
b1 -
b0 ,
b1 )
1'
1!
#2940
0!
#2945
b1 ,
10
1.
1!
#2950
0!
#2955
b10 ,
b1101101 *
00
1/
1!
#2960
0!
#2965
b11 ,
b1101001 *
1!
#2970
0!
#2975
b100 ,
b1100001 *
1!
#2980
0!
#2985
b101 ,
0/
0.
1!
#2990
0!
#2995
b110 ,
10
1.
1!
#3000
0!
#3005
b111 ,
1!
#3010
0!
#3015
b1000 ,
00
0.
1!
#3020
0!
#3025
b0 ,
b0 -
1!
#3030
0!
#3035
b1 ,
b10 )
0'
1!
#3040
0!
#3045
b10 ,
1!
#3050
0!
#3055
b1 -
b0 ,
b1 )
1'
1!
#3060
0!
#3065
b1 ,
10
1.
1!
#3070
0!
#3075
b10 ,
b1100011 *
1&
1/
0.
1!
#3080
0!
#3085
b11 ,
00
1!
#3090
0!
#3095
b100 ,
1!
#3100
0!
#3105
b101 ,
b1110011 *
10
0/
1!
#3110
0!
#3115
b110 ,
b1010011 *
0&
00
1.
1!
#3120
0!
#3125
b111 ,
10
1!
#3130
0!
#3135
b1000 ,
00
0.
1!
#3140
0!
#3145
b0 ,
b0 -
1!
#3150
0!
#3155
b1 ,
b10 )
0'
1!
#3160
0!
#3165
b10 ,
1!
#3170
0!
#3175
b1 -
b0 ,
b1 )
1'
1!
#3180
0!
#3185
b1 ,
10
1.
1!
#3190
0!
#3195
b10 ,
b1010001 *
00
1/
1!
#3200
0!
#3205
b11 ,
b1010101 *
1&
10
0.
1!
#3210
0!
#3215
b100 ,
00
1!
#3220
0!
#3225
b101 ,
b1000101 *
0&
0/
1.
1!
#3230
0!
#3235
b110 ,
0.
1!
#3240
0!
#3245
b111 ,
10
1.
1!
#3250
0!
#3255
b1000 ,
00
0.
1!
#3260
0!
#3265
b0 ,
b0 -
1!
#3270
0!
#3275
b1 ,
b10 )
0'
1!
#3280
0!
#3285
b10 ,
1!
#3290
0!
#3295
b1 -
b0 ,
b1 )
1'
1!
#3300
0!
#3305
b1 ,
10
1.
1!
#3310
0!
#3315
b10 ,
b1000111 *
1&
1/
0.
1!
#3320
0!
#3325
b11 ,
1.
1!
#3330
0!
#3335
b100 ,
00
0.
1!
#3340
0!
#3345
b101 ,
b1010111 *
10
0/
1!
#3350
0!
#3355
b110 ,
b1110111 *
1!
#3360
0!
#3365
b111 ,
b110111 *
0&
00
1.
1!
#3370
0!
#3375
b1000 ,
0.
1!
#3380
0!
#3385
b0 ,
b0 -
1!
#3390
0!
#3395
b1 ,
b10 )
0'
1!
#3400
0!
#3405
b10 ,
1!
#3410
0!
#3415
b11 ,
1!
#3420
0!
#3425
b1 -
b0 ,
b1 )
1'
1!
#3430
0!
#3435
b1 ,
10
1.
1!
#3440
0!
#3445
b10 ,
b110101 *
00
1/
1!
#3450
0!
#3455
b11 ,
b110001 *
1!
#3460
0!
#3465
b100 ,
b111001 *
1&
10
0.
1!
#3470
0!
#3475
b101 ,
b101001 *
0&
00
0/
1.
1!
#3480
0!
#3485
b110 ,
10
1!
#3490
0!
#3495
b111 ,
00
0.
1!
#3500
0!
#3505
b1000 ,
1!
#3510
0!
#3515
b0 ,
b0 -
1!
#3520
0!
#3525
b1 ,
b10 )
0'
1!
#3530
0!
#3535
b10 ,
1!
#3540
0!
#3545
b11 ,
1!
#3550
0!
#3555
b1 -
b0 ,
b1 )
1'
1!
#3560
0!
#3565
b1 ,
10
1.
1!
#3570
0!
#3575
b10 ,
b101011 *
1&
1/
0.
1!
#3580
0!
#3585
b11 ,
00
1!
#3590
0!
#3595
b100 ,
10
1.
1!
#3600
0!
#3605
b101 ,
b111011 *
0/
0.
1!
#3610
0!
#3615
b110 ,
b11011 *
0&
00
1.
1!
#3620
0!
#3625
b111 ,
0.
1!
#3630
0!
#3635
b1000 ,
1!
#3640
0!
#3645
b0 ,
b0 -
1!
#3650
0!
#3655
b1 ,
b10 )
0'
1!
#3660
0!
#3665
b10 ,
1!
#3670
0!
#3675
b11 ,
1!
#3680
0!
#3685
b100 ,
1!
#3690
0!
#3695
b1 -
b0 ,
b1 )
1'
1!
#3700
0!
#3705
b1 ,
10
1.
1!
#3710
0!
#3715
b10 ,
b11001 *
00
1/
1!
#3720
0!
#3725
b11 ,
b11101 *
1&
10
0.
1!
#3730
0!
#3735
b100 ,
1.
1!
#3740
0!
#3745
b101 ,
b1101 *
0&
00
0/
1!
#3750
0!
#3755
b110 ,
0.
1!
#3760
0!
#3765
b111 ,
1!
#3770
0!
#3775
b1000 ,
1!
#3780
0!
#3785
b0 ,
b0 -
1!
#3790
0!
#3795
b1 ,
b10 )
0'
1!
#3800
0!
#3805
b10 ,
1!
#3810
0!
#3815
b11 ,
1!
#3820
0!
#3825
b100 ,
1!
#3830
0!
#3835
b101 ,
1!
#3840
0!
#3845
b110 ,
1(
1'
1!
#3850
0!
#3855
b111 ,
1!
#3860
0!
#3865
b0 ,
b10 -
b0 )
0'
1!
